[
  {
    "slug": "driver-license-reissue",
    "title": "운전면허증 재발급 인터넷 신청 방법·수수료 정보 총정리",
    "excerpt": "운전면허증 분실·훼손 시 재발급받는 온라인·방문 방법과 종류별 수수료, 주의사항을 공식 절차 기준으로 정리했습니다.",
    "date": "2026-07-20T09:00:00",
    "category": "생활정보",
    "cta": [
      {
        "label": "운전면허증 재발급 방법 자세히 보기",
        "href": "https://zucca100.com/driver-license-request/"
      },
      {
        "label": "안전운전 통합민원 재발급 안내 바로가기",
        "href": "https://zucca100.com/driver-license-request/"
      },
      {
        "label": "지금 바로 재발급 절차 확인하기",
        "href": "https://zucca100.com/driver-license-request/"
      }
    ],
    "contentHtml": "<h2>운전면허증 재발급이 필요한 경우</h2><p>운전면허증을 잃어버렸거나(분실), 물에 젖거나 훼손되어 알아보기 어려울 때, 또는 사진을 새로 바꾸고 싶을 때 재발급을 신청합니다. 운전면허증재발급은 크게 <strong>인터넷(온라인) 신청</strong>과 <strong>방문 신청</strong> 두 가지로 나뉘며, 상황에 따라 처리 속도와 준비물이 조금씩 다릅니다.</p><p>운전면허 분실 재발급, 운전면허증 인터넷발급, 운전면허증 갱신 재발급처럼 검색어는 다양하지만 실제 처리 창구는 동일하게 <strong>도로교통공단 안전운전 통합민원</strong>입니다.</p><!--CTA:0--><h2>온라인 신청 방법 (안전운전 통합민원)</h2><p>가장 간편한 방법은 도로교통공단이 운영하는 안전운전 통합민원 웹사이트를 이용하는 것입니다. 대략적인 절차는 다음과 같습니다.</p><ol><li>안전운전 통합민원 홈페이지 접속</li><li>[운전면허증 발급] → [면허증 재발급] 메뉴 선택</li><li>간편인증(카카오·네이버 등) 또는 공동인증서로 본인확인</li><li>약관 동의 후 수령 방법(방문 수령)과 수령처·날짜 지정</li><li>수수료 결제 후 신청 완료</li></ol><p>온라인 신청은 24시간 가능해 평일에 시간 내기 어려운 경우 유용합니다. 다만 신청 후에는 취소·변경이 어려울 수 있으니 수령처와 날짜를 신중히 선택하세요.</p><h2>방문 신청 방법 (즉시 발급)</h2><p>면허증이 당장 필요하다면 <strong>운전면허시험장</strong>을 직접 방문하는 것이 가장 빠릅니다. 신분증과 사진을 지참하면 접수 후 대체로 당일(대기 상황에 따라 1시간 내외) 발급받을 수 있습니다. 가까운 <strong>경찰서 민원실</strong>에서도 접수할 수 있으나, 이 경우 임시 면허증을 받은 뒤 실물 카드는 며칠 뒤 수령하는 방식이라 시간이 더 걸립니다.</p><h2>종류별 수수료</h2><p>수수료는 면허증 종류에 따라 다릅니다(공식 고지 기준이며 변동될 수 있습니다).</p><ul><li>일반 국문·영문 운전면허증: 약 10,000원</li><li>모바일 IC 운전면허증: 약 15,000원</li></ul><p>사진을 새로 바꾸려면 6개월 이내 촬영한 여권용 규격 사진(3.5×4.5cm)이 필요합니다. 기존 사진을 그대로 쓰는 경우에는 사진 없이 신청할 수 있습니다.</p><p><strong>본인에게 맞는 재발급 방법과 준비물을 한 번에 확인해 보세요.</strong></p><!--CTA:1--><h2>재발급 전 알아두면 좋은 점</h2><ul><li>분실 신고와 재발급은 함께 처리되므로 별도의 분실 신고 절차가 없어도 됩니다.</li><li>온라인 신청은 실물 카드를 즉시 받는 것이 아니라 지정한 날짜에 방문 수령하는 방식입니다.</li><li>모바일 신분증(모바일 운전면허증)을 함께 쓰려면 IC 면허증으로 발급받아야 연동이 편리합니다.</li></ul><h2>자주 묻는 질문</h2><p><strong>Q. 운전면허증을 잃어버렸는데 운전해도 되나요?</strong> 재발급 신청 후 임시 운전면허증(또는 모바일 확인)을 발급받으면 그 기간 동안 운전이 가능합니다. 다만 실물 없이 운전하다 단속되면 확인 절차가 번거로울 수 있으니 빠르게 재발급받는 것이 좋습니다.</p><p><strong>Q. 온라인으로 신청하면 집으로 배송되나요?</strong> 운전면허증은 본인 확인이 필요해 지정한 시험장·경찰서에서 방문 수령하는 것이 기본입니다.</p><p><strong>Q. 지방에서도 어디서나 재발급이 가능한가요?</strong> 전국 운전면허시험장과 경찰서 민원실에서 신청할 수 있어 주소지와 무관하게 처리할 수 있습니다.</p><p><strong>가까운 창구와 정확한 수수료, 준비물을 지금 확인하고 한 번에 처리하세요.</strong></p><!--CTA:2-->"
  },
  {
    "slug": "car-tax-annual",
    "title": "자동차세 연납 신청 방법·할인율 정보 총정리 (2026년)",
    "excerpt": "자동차세를 미리 한 번에 내고 할인받는 연납 제도의 신청 시기, 2026년 할인율, 납부 방법과 주의사항을 정리했습니다.",
    "date": "2026-07-19T09:00:00",
    "category": "생활정보",
    "cta": [
      {
        "label": "자동차세 연납 신청 방법 자세히 보기",
        "href": "https://zucca100.com/car-tax/"
      },
      {
        "label": "위택스 자동차세 조회·납부 바로가기",
        "href": "https://zucca100.com/car-tax/"
      },
      {
        "label": "지금 바로 연납 할인 확인하기",
        "href": "https://zucca100.com/car-tax/"
      }
    ],
    "contentHtml": "<h2>자동차세 연납이란</h2><p>자동차세는 원래 1년에 두 번(상반기·하반기) 나눠 냅니다. <strong>연납(선납)</strong>은 이 세금을 연초에 한꺼번에 미리 납부하고, 남은 기간에 해당하는 만큼 세액을 할인받는 제도입니다. 자동차세 연납신청, 자동차세 미리납부, 자동차세 선납 할인은 모두 같은 제도를 가리키는 표현입니다.</p><!--CTA:0--><h2>연납 신청 시기와 할인율 (2026년 기준)</h2><p>연납은 1월, 3월, 6월, 9월 네 차례 신청할 수 있고, <strong>일찍 신청할수록 할인 폭이 큽니다.</strong> 2026년 1월 연납의 경우 남은 11개월분에 공제가 적용되어 연 세액 대비 <strong>약 4.58%</strong> 수준의 할인율이 적용됩니다.</p><p>할인율은 정부 정책에 따라 매년 조정되어 왔으므로(최근 몇 년간 단계적으로 낮아지는 추세), 신청 전 위택스나 관할 지자체 공지에서 그해 확정 할인율을 확인하는 것이 정확합니다.</p><h2>자동차세 조회·납부 방법 3가지</h2><ul><li><strong>위택스(WeTax)</strong> 공식 홈페이지 — 지방세 통합 조회·납부</li><li><strong>스마트위택스</strong> 모바일 앱 — 스마트폰에서 간편 납부</li><li>네이버페이·카카오페이 등 <strong>간편결제 연동</strong> — 빠르지만 명의 일치가 필요</li></ul><p><strong>내 차의 연납 세액과 할인 금액을 지금 조회해 보세요.</strong></p><!--CTA:1--><h2>정기분 납부 시기와 대상</h2><p>연납을 하지 않으면 정기분으로 납부하게 됩니다.</p><ul><li>제1기분(상반기): 6월 16일~30일, 6월 1일 기준 소유자</li><li>제2기분(하반기): 12월 16일~31일, 12월 1일 기준 소유자</li><li>연세액 10만 원 미만 차량(경차·일부 화물차 등): 6월에 1년치를 한 번에 부과</li></ul><h2>네이버·간편결제 오류가 날 때</h2><p>간편결제에서 조회·납부가 되지 않는 가장 흔한 원인은 <strong>차량 소유자 명의와 인증서(간편인증) 명의가 다른 경우</strong>입니다. 이럴 때는 위택스 공식 홈페이지에 직접 접속해 납부하거나, 소유자 본인 명의로 인증을 진행하면 해결되는 경우가 많습니다. 신청 마감일에는 접속이 몰려 지연될 수 있으니 여유 있게 처리하는 것이 좋습니다.</p><h2>체납 시 불이익</h2><p>납부 기한을 넘기면 <strong>3%의 납부지연가산세</strong>가 붙고, 장기 체납 시 번호판 영치나 차량 압류로 이어질 수 있습니다. 소액이라도 기한 내 납부하는 것이 안전합니다.</p><h2>자주 묻는 질문</h2><p><strong>Q. 연납을 신청했다가 중간에 차를 팔면 어떻게 되나요?</strong> 차량을 매도·폐차하면 이미 낸 세금 중 남은 기간분은 환급됩니다.</p><p><strong>Q. 1월을 놓쳤는데 연납이 아예 불가능한가요?</strong> 3월·6월·9월에도 신청할 수 있습니다. 다만 남은 개월수가 줄어들어 할인 폭은 작아집니다.</p><p><strong>Q. 경차도 연납 할인이 되나요?</strong> 연세액이 10만 원 미만이면 6월에 1년치를 한 번에 부과받는 경우가 많아, 연납 실익이 크지 않을 수 있습니다.</p><p><strong>올해 확정 할인율과 내 차 세액을 지금 바로 확인해 보세요.</strong></p><!--CTA:2-->"
  },
  {
    "slug": "mobile-id-issue",
    "title": "모바일 신분증 발급 방법·사용처 정보 총정리",
    "excerpt": "스마트폰에 담는 모바일 신분증(모바일 운전면허증·주민등록증)의 발급 방법 두 가지와 사용처, 자주 나는 오류 해결법을 정리했습니다.",
    "date": "2026-07-18T09:00:00",
    "category": "통신/IT",
    "cta": [
      {
        "label": "모바일 신분증 발급 방법 자세히 보기",
        "href": "https://zucca100.com/mobile-id/"
      },
      {
        "label": "모바일 신분증 앱 안내 바로가기",
        "href": "https://zucca100.com/mobile-id/"
      },
      {
        "label": "지금 바로 발급 절차 확인하기",
        "href": "https://zucca100.com/mobile-id/"
      }
    ],
    "contentHtml": "<h2>모바일 신분증이란</h2><p>모바일 신분증은 실물 주민등록증·운전면허증을 스마트폰 앱에 담아 사용하는 국가 공인 신분증입니다. 모바일신분증발급, 모바일 운전면허증, 모바일 주민등록증은 모두 <strong>‘대한민국 모바일 신분증’ 공식 앱</strong>을 통해 이용합니다. 실물과 동일한 효력을 가지며, 위·변조 방지를 위해 실시간 검증 기술이 적용됩니다.</p><!--CTA:0--><h2>발급 방법 2가지</h2><p>발급 방식은 크게 두 가지입니다.</p><ul><li><strong>IC 신분증 연동 방식</strong> — IC칩이 있는 주민등록증·운전면허증을 앱에서 NFC로 태그해 발급. IC 신분증을 새로 만들어야 한다면 실물 발급 수수료가 듭니다.</li><li><strong>주민센터 현장 QR 발급 방식</strong> — 가까운 주민센터를 방문해 본인확인 후 QR 코드를 스캔해 발급. 앱 발급 자체는 무료입니다.</li></ul><p>공통 절차는 ‘앱 설치 → 본인인증 → NFC 태그 또는 QR 스캔 → 안면인식 등록’ 순으로 진행됩니다.</p><h2>어디에 사용할 수 있나요</h2><p>모바일 신분증은 관공서 민원, 은행·증권 등 금융 창구, 공항, 편의점·주류 판매 등 오프라인 성인 확인 등 실물 신분증이 필요한 대부분의 상황에서 사용할 수 있습니다. 다만 제시받는 기관이 모바일 신분증 확인 방식을 지원해야 하므로, 현장에서 지원 여부를 확인하면 좋습니다.</p><p><strong>내 스마트폰에 맞는 발급 방법을 지금 확인해 보세요.</strong></p><!--CTA:1--><h2>사본(캡처) 제출은 왜 거절될까</h2><p>모바일 신분증 화면을 <strong>캡처한 이미지</strong>는 실시간 검증이 되지 않기 때문에 정식 신분 확인으로 인정되지 않는 경우가 많습니다. 제출·확인이 필요할 때는 캡처본이 아니라 앱에서 그때그때 생성되는 QR 코드나 실시간 화면을 제시해야 합니다.</p><h2>자주 나는 오류와 해결</h2><ul><li><strong>NFC 인식 실패</strong> — 스마트폰 NFC 기능이 켜져 있는지, IC 신분증을 카메라 부근 등 NFC 안테나 위치에 정확히 대고 있는지 확인합니다.</li><li><strong>스마트폰 교체 시</strong> — 기기를 바꾸면 기존 모바일 신분증은 사용 중지되고 새 기기에서 다시 발급해야 합니다.</li><li><strong>안면인식 오류</strong> — 밝은 곳에서 얼굴 전체가 보이도록 다시 시도합니다.</li></ul><h2>자주 묻는 질문</h2><p><strong>Q. 실물 신분증이 없어도 되나요?</strong> 모바일 신분증은 실물과 동일한 효력을 갖지만, 아직 모든 곳이 지원하지는 않으므로 당분간 실물도 함께 소지하는 것이 안전합니다.</p><p><strong>Q. 발급 비용이 드나요?</strong> 주민센터 QR 발급 등 앱 발급 자체는 무료입니다. 다만 IC 신분증 실물을 새로 만들어야 하면 그 발급 수수료가 별도로 듭니다.</p><p><strong>지금 바로 나에게 맞는 모바일 신분증 발급 절차를 확인해 보세요.</strong></p><!--CTA:2-->"
  },
  {
    "slug": "parental-leave-pay",
    "title": "육아휴직급여 신청 방법·금액 정보 총정리 (2026년)",
    "excerpt": "2026년 개편된 육아휴직급여의 지급 금액과 상한액, 6+6 부모공동육아휴직제, 고용24 신청 방법과 자격 요건을 정리했습니다.",
    "date": "2026-07-17T09:00:00",
    "category": "정부지원/정책",
    "cta": [
      {
        "label": "육아휴직급여 신청 방법 자세히 보기",
        "href": "https://zucca100.com/parental-leave-benefits/"
      },
      {
        "label": "고용24 육아휴직급여 안내 바로가기",
        "href": "https://zucca100.com/parental-leave-benefits/"
      },
      {
        "label": "지금 바로 지급액·자격 확인하기",
        "href": "https://zucca100.com/parental-leave-benefits/"
      }
    ],
    "contentHtml": "<h2>육아휴직급여란</h2><p>육아휴직급여는 자녀 양육을 위해 육아휴직을 사용한 근로자에게 고용보험에서 급여를 지원하는 제도입니다. 육아휴직급여신청, 육아휴직 급여 금액, 육아휴직 급여 계산, 육아휴직 급여 지급일이 모두 이 제도와 관련된 검색어입니다. 2026년에는 지급 방식과 상한액이 크게 개편되었습니다.</p><!--CTA:0--><h2>2026년 지급 금액과 상한액</h2><p>2026년 기준 일반 육아휴직급여는 다음과 같이 지급됩니다(개인의 통상임금에 따라 실제 금액은 달라집니다).</p><ul><li>1~3개월: 통상임금의 100%, 월 상한 약 250만 원</li><li>4~6개월: 통상임금의 100%, 월 상한 약 200만 원</li><li>7개월 이후: 통상임금의 80%, 월 상한 약 160만 원</li></ul><p>과거에는 급여의 일부(약 25%)를 복직 후 일정 기간 근무해야 주는 <strong>사후지급금</strong> 제도가 있었지만, 2026년에는 이 제도가 폐지되어 <strong>휴직 기간 중 전액을 매달 받는</strong> 방식으로 바뀌었습니다.</p><h2>6+6 부모공동육아휴직제</h2><p>생후 18개월 이내 자녀를 두고 부모가 함께(동시 또는 순차로) 육아휴직을 사용하면, 첫 6개월간 부모 모두 통상임금 100%를 받고 월 상한이 매달 올라갑니다. 상한은 1개월차 250만 원에서 시작해 <strong>6개월차 최대 450만 원</strong>까지 단계적으로 인상됩니다.</p><p><strong>내 통상임금 기준 실제 지급액을 지금 확인해 보세요.</strong></p><!--CTA:1--><h2>신청 자격</h2><ul><li>고용보험에 가입한 근로자로서 육아휴직을 30일 이상 부여받았을 것</li><li>육아휴직 시작일 이전 피보험 단위기간이 통산 180일 이상일 것</li></ul><h2>고용24 신청 방법</h2><ol><li>회사(사업주)가 육아휴직 확인서를 전산 등록</li><li>근로자가 육아휴직급여 신청서 작성 및 필요 서류 제출</li><li>고용24 포털(온라인) 또는 관할 고용센터(방문·우편)로 접수</li></ol><p>신청은 육아휴직을 시작한 뒤 1개월이 지난 시점부터 가능하며, <strong>휴직 종료 후 12개월 이내</strong>에 신청하지 않으면 받을 수 없으니 기한에 유의하세요.</p><h2>지급일</h2><p>신청이 접수·심사되면 대체로 영업일 기준 14일 이내에 지급되고, 2회차 신청부터는 처리가 더 빨라지는 편입니다. 제도의 금액·기간은 매년 바뀔 수 있으므로 신청 전 고용24에서 최신 기준을 확인하세요.</p><h2>자주 묻는 질문</h2><p><strong>Q. 자영업자도 받을 수 있나요?</strong> 육아휴직급여는 고용보험에 가입한 근로자 대상 제도입니다. 자영업자·특수고용직 등은 별도의 지원 사업 대상 여부를 확인해야 합니다.</p><p><strong>Q. 한 번에 신청하나요, 매달 신청하나요?</strong> 보통 1개월 단위로 신청·지급받습니다.</p><p><strong>지금 바로 2026년 기준 지급액과 신청 절차를 확인해 보세요.</strong></p><!--CTA:2-->"
  },
  {
    "slug": "gyeonggi-youth-point",
    "title": "경기도 청년 복지포인트 신청 방법·자격 정보 총정리",
    "excerpt": "중소기업 재직 청년에게 연 120만 원 상당을 지원하는 경기도 청년 복지포인트의 자격, 제출 서류, 신청 방법과 사용처를 정리했습니다.",
    "date": "2026-07-16T09:00:00",
    "category": "정부지원/정책",
    "cta": [
      {
        "label": "청년 복지포인트 신청 방법 자세히 보기",
        "href": "https://zucca100.com/youth-welfare-point/"
      },
      {
        "label": "청년 복지포인트 자격·서류 바로가기",
        "href": "https://zucca100.com/youth-welfare-point/"
      },
      {
        "label": "지금 바로 신청 자격 확인하기",
        "href": "https://zucca100.com/youth-welfare-point/"
      }
    ],
    "contentHtml": "<h2>경기도 청년 복지포인트란</h2><p>경기도 청년 복지포인트는 중소·중견기업 등에 다니는 청년의 복지 격차를 줄이기 위해 <strong>연 120만 원 상당의 포인트</strong>를 지원하는 경기도 사업입니다. 청년복지포인트 신청, 경기도 청년 복지포인트 자격, 청년 복지포인트 사용처가 자주 찾는 검색어입니다.</p><p>이 제도는 지방자치단체 사업이라 <strong>신청 기간과 세부 기준이 해마다 달라지고</strong>, 지역·연도별로 예산 규모가 다릅니다. 아래 내용은 일반적인 기준이며, 신청 전 반드시 경기도 공식 공고에서 그해 기준을 확인해야 합니다.</p><!--CTA:0--><h2>신청 자격</h2><ul><li>만 19~39세 경기도 주민등록 거주자</li><li>경기도 소재 중소·중견기업, 소상공인, 비영리법인 등에 재직</li><li>주 36시간 이상 상근 근무</li><li>건강보험료 기준 등 소득 요건 충족(기준액은 연도별로 고시)</li></ul><h2>지급액과 사용처</h2><p>선정되면 연 120만 원 상당을 보통 2회로 나눠 포인트로 지급받습니다. 포인트는 경기도가 운영하는 <strong>청년몰</strong> 등에서 도서, 온라인 강의, 전자기기, 헬스장, 숙박 등 정해진 항목에 사용할 수 있으며, <strong>사용 유효기한</strong>이 있으니 기한 내에 쓰는 것이 중요합니다.</p><p><strong>내가 신청 대상인지 지금 자격 요건을 확인해 보세요.</strong></p><!--CTA:1--><h2>제출 서류</h2><ul><li>주민등록초본(주민등록번호 뒷자리 포함, 최신 발급본)</li><li>4대 사회보험 가입자 가입내역 확인서</li><li>건강보험료 납부확인서(최근 6개월분)</li><li>직장 가입자 개인별 자격조회 내역서</li><li>사업자등록증 사본(재직 회사)</li></ul><h2>신청 방법과 주의사항</h2><p>신청은 정해진 기간에 <strong>온라인으로 서류를 접수</strong>하는 방식입니다. 마감일에는 접속이 몰려 지연되기 쉬우므로 서류를 미리 스캔(PDF)해 두고 여유 있게 제출하세요. 건강보험료 기준 오류가 탈락의 흔한 원인이니, 납부확인서 금액을 공고 기준과 꼭 대조해 보는 것이 좋습니다.</p><h2>자주 묻는 질문</h2><p><strong>Q. 다른 시·도에도 비슷한 제도가 있나요?</strong> 청년 복지·자산형성 지원은 지자체마다 명칭과 조건이 다릅니다. 거주·재직 지역의 청년 정책 포털을 함께 확인하세요.</p><p><strong>Q. 이직하면 자격이 사라지나요?</strong> 선정 이후 재직 요건을 유지해야 하는 경우가 많아, 퇴사·이직 시에는 공고의 유지 조건을 확인해야 합니다.</p><p><strong>지금 바로 올해 신청 기간과 자격 기준을 확인해 보세요.</strong></p><!--CTA:2-->"
  },
  {
    "slug": "worknet-jobseeker",
    "title": "워크넷 구직등록 방법·실업급여 연계 정보 총정리",
    "excerpt": "고용노동부 대표 취업포털 워크넷의 구직등록·이력서 작성 방법과 실업급여 구직활동 연계, 채용정보 검색 기능을 정리했습니다.",
    "date": "2026-07-15T09:00:00",
    "category": "취업",
    "cta": [
      {
        "label": "워크넷 구직등록 방법 자세히 보기",
        "href": "https://zucca100.com/work-net/"
      },
      {
        "label": "워크넷 채용정보·이력서 바로가기",
        "href": "https://zucca100.com/work-net/"
      },
      {
        "label": "지금 바로 구직등록 시작하기",
        "href": "https://zucca100.com/work-net/"
      }
    ],
    "contentHtml": "<h2>워크넷이란</h2><p>워크넷은 고용노동부와 한국고용정보원이 운영하는 대표 취업 포털입니다. 워크넷 구직등록, 워크넷 이력서, 워크넷 채용정보, 워크넷 실업급여 검색이 자주 쓰이며, 현재는 <strong>워크24 통합 서비스</strong> 안에서 함께 이용합니다. 민간 채용 사이트와 달리 공공 일자리와 정부 지원 채용정보를 폭넓게 볼 수 있는 것이 특징입니다.</p><!--CTA:0--><h2>구직등록 방법</h2><ol><li>워크넷(워크24) 접속 후 간편인증으로 로그인</li><li>이력서와 자기소개서 작성</li><li>희망 근무지역·직무·희망연봉 등 조건 입력</li><li>‘구직신청하기’를 눌러 구직 상태로 전환 → <strong>구직등록번호</strong> 발급</li></ol><p>이력서만 저장해 둔 상태와, ‘구직신청’까지 완료해 구직등록번호가 나온 상태는 다릅니다. 실업급여 등과 연계하려면 <strong>구직신청까지 완료</strong>해야 합니다.</p><h2>이력서 작성 팁</h2><p>이력서 제목에 핵심 경력·직무를 명시하고, 희망 조건을 명확히 적을수록 기업의 면접 제안을 받을 확률이 올라갑니다. 워크넷은 직업선호도·직업심리검사(L형·S형)를 무료로 제공하므로, 방향을 정하기 어렵다면 검사 결과를 참고할 수 있습니다.</p><p><strong>지금 바로 구직등록 절차를 확인하고 시작해 보세요.</strong></p><!--CTA:1--><h2>실업급여와의 연계</h2><p>실업급여(구직급여)를 받으려면 워크넷 구직등록이 기본 전제 중 하나입니다. 워크넷을 통한 입사지원·구직활동 내역은 시스템에 기록되어 <strong>구직활동 증빙 자료로 연계</strong>되므로, 매번 별도 서류를 준비하는 부담이 줄어듭니다. 다만 형식적인 무분별 지원은 정상적인 구직활동으로 인정되지 않을 수 있으니 실제 관심 있는 공고에 지원하는 것이 좋습니다.</p><h2>채용정보 검색 기능</h2><ul><li>정부가 인증한 <strong>강소기업·청년친화 강소기업</strong> 필터링</li><li>조건 기반 <strong>맞춤 채용정보 추천</strong></li><li>지역·직종·고용형태별 상세 검색</li></ul><h2>자주 묻는 질문</h2><p><strong>Q. 재직 중에도 구직등록을 할 수 있나요?</strong> 가능합니다. 다만 실업급여 목적이라면 이직 후 요건을 갖춘 뒤 신청해야 합니다.</p><p><strong>Q. 구직등록만 하면 실업급여를 받나요?</strong> 아닙니다. 구직등록은 여러 요건 중 하나이며, 이직 사유·피보험 기간 등 수급 요건을 별도로 충족해야 합니다.</p><p><strong>지금 바로 워크넷 구직등록을 시작해 보세요.</strong></p><!--CTA:2-->"
  },
  {
    "slug": "unemployment-benefit-application",
    "title": "실업급여(구직급여) 신청방법 총정리 — 대상·조건부터 고용24 신청까지",
    "excerpt": "실업급여(구직급여) 신청 절차와 고용24 온라인·모바일·방문 신청 방법을 정리하고, 대상·계산·실업인정 등 자세한 내용은 주제별 글로 안내합니다.",
    "date": "2026-07-22T09:00:00",
    "category": "생활정보",
    "cta": [
      {
        "label": "지금 바로 실업급여 신청하기",
        "href": "https://m.work24.go.kr/cm/c/f/1100/selecSystInfo.do?systCnntId=CI00001715&systId=SI00000411"
      },
      {
        "label": "실업급여 계산기로 예상 수급액 확인하기",
        "href": "https://zucca100.com/%ec%8b%a4%ec%97%85%ea%b8%89%ec%97%ac-%ea%b3%84%ec%82%b0%ea%b8%b0-%ec%88%98%ea%b8%89-%eb%8c%80%ec%83%81-%ec%a1%b0%ea%b1%b4-%ec%95%88%eb%82%b4/"
      },
      {
        "label": "고용24 홈페이지에서 신청 절차 확인하기",
        "href": "https://www.work24.go.kr/cm/main.do"
      },
      {
        "label": "지금 바로 고용24 바로가기",
        "href": "https://www.work24.go.kr/cm/main.do"
      }
    ],
    "contentHtml": "<h2>실업급여(구직급여)란? 실업수당과 같은 말인가요?</h2><p>실업급여는 고용보험에 가입한 근로자가 비자발적으로 퇴사한 뒤 재취업 활동을 하는 동안 생활 안정과 구직 활동을 지원하기 위해 지급하는 급여입니다. 법령상 정식 명칭은 구직급여이며, 실업급여구직급여·구직급여실업급여처럼 두 단어를 붙여 검색해도 결국 같은 제도를 가리킵니다. 실업수당신청, 실업수당조건이라는 표현으로 찾는 경우도 많은데, 이 역시 구직급여를 뜻하는 일상적인 표현입니다. 구직급여내용을 한 문장으로 요약하면 '비자발적 이직자에게 재취업 활동 기간 동안 지급하는 급여'입니다.</p><p>실업급여 관련 정보는 구직급여디시(디시인사이드)를 비롯한 여러 커뮤니티에도 후기가 많이 올라오지만, 지급 기준과 금액은 매년 바뀔 수 있으므로 실업급여문의나 실업급여상담이 필요할 때는 고용노동부 고객상담센터(국번없이 1350)나 관할 고용센터, 사안이 복잡한 경우라면 실업급여노무사와의 상담을 통해 정확한 기준을 확인하는 것이 안전합니다.</p><!--CTA:0--><h2>실업급여 신청방법 — 고용24 온라인·모바일·방문 절차</h2><p>고용노동부실업급여신청방법(고용24실업급여신청방법, 실업급여신청방법고용24)과 구직급여신청방법(구직급여방법, 실업급여방법)의 기본 흐름은 다음과 같습니다.</p><p>1. 퇴사한 회사(사업주)에 이직확인서 발급을 요청합니다.<br>2. 고용24 홈페이지 또는 워크넷에서 구직신청을 합니다.<br>3. 관할 고용센터를 방문(또는 온라인)하여 수급자격신청자온라인교육(구직급여교육)을 이수합니다.<br>4. 수급자격 인정신청서를 제출하면, 통상 접수일로부터 14일 이내에 수급자격 인정 여부가 통지됩니다.<br>5. 이후 실업인정일마다 구직활동 내역을 보고하며 실업급여를 지급받습니다.</p><p>실업급여신청방법순서(실업급여신청방법절차)를 요약하면 위와 같으며, 실업급여신청방법준비물로는 신분증, 통장 사본, 이직확인서 처리 여부 확인 등이 필요합니다. 실업급여신청방법온라인(실업급여모바일, 실업급여모바일신청방법)을 이용하면 최초 구직신청과 이후 실업인정 재신청 상당 부분을 PC나 스마트폰으로 처리할 수 있지만, 최초 수급자격 인정신청과 1차 실업인정만큼은 원칙적으로 고용센터 방문이 필요합니다. 반대로 실업급여신청방법방문을 원한다면 신분증을 지참해 관할 고용센터를 찾아가면 됩니다.</p><p>고용보험실업급여신청(고용보험실업급여신청방법)에 필요한 고용보험실업급여신청서류(구직급여서류)는 신분증과 통장 사본이 기본이며, 이직 사유에 따라 추가 서류가 요구될 수 있습니다. 신청 자격 자체가 궁금하다면 고용보험실업급여신청조건을 먼저 확인해야 하는데, 자세한 대상·조건 기준은 아래 별도 글에서 다룹니다. 고용보험실업급여신청기간은 원칙적으로 퇴사(이직) 다음 날부터 12개월 이내로 정해져 있으므로, 실업급여신청기간(구직급여신청기간)을 넘기지 않도록 퇴사 후에는 되도록 빨리 구직급여신청(실업급여신청)을 진행하는 것이 좋습니다.</p><p>실업급여신청하기(실업급여신청하는곳)가 막막하다면 결국 고용24 홈페이지가 출발점입니다. 구직급여신청하는방법, 구직급여신청하는법, 실업급여신청하는방법, 실업급여신청하는법, 실업급여타는방법, 실업급여타는법처럼 표현은 조금씩 달라도 모두 위 절차를 가리키는 같은 질문입니다.</p><p>2024실업급여신청방법과 2025실업급여신청방법을 검색해서 들어오는 분들도 많은데, 기본적인 신청 절차와 서류 자체는 해마다 크게 달라지지 않았고, 매년 바뀌는 부분은 주로 상한액·하한액 같은 금액과 지급 대상 확대 여부입니다. 따라서 연도별 신청방법을 따로 외울 필요 없이, 위에서 소개한 최신 고용24 절차를 그대로 따르면 됩니다.</p><!--CTA:2--><h2>대상, 계산, 실업인정까지 — 주제별로 더 자세히 알아보기</h2><p>실업급여는 신청 절차 외에도 내가 대상자인지, 얼마를 받을 수 있는지, 실업인정은 어떻게 진행되는지가 함께 궁금해지는 경우가 많습니다. 아래 글에서 주제별로 나누어 자세히 정리했습니다.</p><p style=\"margin:32px 0;text-align:center;\"><a href=\"/posts/unemployment-benefit-eligibility\" style=\"display:inline-block;width:100%;max-width:420px;padding:14px 20px;border-radius:8px;background-color:#03C75A;color:#ffffff;font-weight:700;font-size:1.05rem;line-height:1.4;text-decoration:none;text-align:center;\">실업급여 대상·조건 총정리 보러가기</a></p><p><strong>내 예상 수급액이 궁금하다면 실업급여 계산기를 먼저 확인해보세요.</strong></p><!--CTA:1--><p>계산 결과가 궁금한 만큼, 상한액·하한액 같은 세부 계산 기준을 미리 알아두면 실제 수급액을 가늠하기 쉬워집니다.</p><p style=\"margin:32px 0;text-align:center;\"><a href=\"/posts/unemployment-benefit-calculator-guide\" style=\"display:inline-block;width:100%;max-width:420px;padding:14px 20px;border-radius:8px;background-color:#03C75A;color:#ffffff;font-weight:700;font-size:1.05rem;line-height:1.4;text-decoration:none;text-align:center;\">구직급여 계산·상한액·하한액 총정리 보러가기</a></p><p>신청 후에는 정해진 주기마다 실업인정을 받아야 하는데, 1차와 2차 이후의 절차가 서로 다릅니다.</p><p style=\"margin:32px 0;text-align:center;\"><a href=\"/posts/unemployment-benefit-recognition-rounds\" style=\"display:inline-block;width:100%;max-width:420px;padding:14px 20px;border-radius:8px;background-color:#03C75A;color:#ffffff;font-weight:700;font-size:1.05rem;line-height:1.4;text-decoration:none;text-align:center;\">실업인정 차수별(1차~8차) 안내 보러가기</a></p><p>실업급여를 받는 동안 지급일, 세금, 국민연금 처리까지 함께 알아두면 수급 기간 내내 헷갈리지 않습니다.</p><p style=\"margin:32px 0;text-align:center;\"><a href=\"/posts/unemployment-benefit-payment-info\" style=\"display:inline-block;width:100%;max-width:420px;padding:14px 20px;border-radius:8px;background-color:#03C75A;color:#ffffff;font-weight:700;font-size:1.05rem;line-height:1.4;text-decoration:none;text-align:center;\">실업급여 지급일·세금·국민연금 등 알아두기</a></p><h2>자주 묻는 질문</h2><p><strong>Q1. 실업급여와 구직급여, 실업수당은 다른 제도인가요?</strong> 아닙니다. 모두 같은 제도를 가리키는 표현이며, 법령상 정식 명칭은 구직급여입니다.</p><p><strong>Q2. 실업급여신청방법후기를 보면 사람마다 절차가 다르다고 하는데 맞나요?</strong> 기본 절차는 동일하지만, 이직 사유와 신청 시점에 따라 요구되는 서류나 세부 절차가 조금씩 달라질 수 있습니다. 상황별 세부 기준은 위 대상·조건 안내 글을 참고하세요.</p><p><strong>Q3. 신청 전에 상담을 받고 싶은데 어디로 연락하면 되나요?</strong> 고용노동부 고객상담센터(국번없이 1350)나 관할 고용센터로 문의하면 되고, 이직 사유가 복잡하거나 다툼의 여지가 있다면 노무사 상담을 받아보는 것도 방법입니다.</p><p><strong>지금 바로 고용24 홈페이지에서 실업급여 신청 절차를 확인해보세요.</strong></p><!--CTA:3-->"
  },
  {
    "slug": "unemployment-benefit-eligibility",
    "title": "실업급여 대상·조건 총정리 — 계약만료·권고사직·정년퇴직·일용직 상황별 안내",
    "excerpt": "실업급여(구직급여) 수급 자격의 기본 조건과, 권고사직·계약만료·정년퇴직·일용직·예술인 등 퇴사 사유별로 달라지는 대상 여부를 정리했습니다.",
    "date": "2026-07-22T09:05:00",
    "category": "생활정보",
    "cta": [
      {
        "label": "내가 대상자인지 고용24에서 확인하기",
        "href": "https://m.work24.go.kr/cm/c/f/1100/selecSystInfo.do?systCnntId=CI00001715&systId=SI00000411"
      },
      {
        "label": "실업급여 계산기로 예상 수급액 확인하기",
        "href": "https://zucca100.com/%ec%8b%a4%ec%97%85%ea%b8%89%ec%97%ac-%ea%b3%84%ec%82%b0%ea%b8%b0-%ec%88%98%ea%b8%89-%eb%8c%80%ec%83%81-%ec%a1%b0%ea%b1%b4-%ec%95%88%eb%82%b4/"
      }
    ],
    "contentHtml": "<h2>실업급여 대상 및 조건 — 실업수당조건 한눈에 보기</h2><p>구직급여대상(실업급여대상, 실업급여대상자)이 되려면 크게 두 가지 조건을 충족해야 합니다. 첫째, 이직일 이전 18개월간 고용보험 피보험단위기간이 합산 180일 이상이어야 합니다. 둘째, 근로 의사와 능력이 있음에도 취업하지 못한 상태여야 하며, 원칙적으로 비자발적으로 이직한 경우여야 합니다. 이 두 가지가 실업급여조건(구직급여조건, 고용보험실업급여조건, 고용보험실업급여신청조건)의 핵심입니다.</p><p>구직급여수급자격(실업급여수급조건)을 스스로 점검해보고 싶다면 실업급여수급자격신청온라인 메뉴, 즉 고용24 홈페이지에서 실업급여대상확인(실업급여조건확인, 실업급여조건조회) 메뉴를 이용하면 됩니다. 흔히 실업급여조건6개월이라고 부르는 것도 결국 위 피보험단위기간 180일(약 6개월) 요건을 가리키는 말입니다. 구직급여수급(실업급여 수급) 여부는 결국 이 두 조건을 실제로 충족하는지에 달려 있습니다.</p><p><strong>내가 대상자인지 확실하지 않다면 고용24에서 바로 확인해보세요.</strong></p><!--CTA:0--><h2>퇴사 사유별로 다른 실업급여 대상 여부</h2><h3>권고사직으로 퇴사한 경우</h3><p>권고사직실업급여신청방법을 찾는 경우가 많은데, 권고사직은 회사의 경영상 필요에 의한 비자발적 이직으로 인정되어 실업급여 대상에 포함됩니다. 다만 실제로는 권고사직인지 자진퇴사인지를 두고 다툼이 생기는 경우가 있으므로, 사직서에 사유를 명확히 남기고 관련 정황(면담 기록, 통보 문서 등)을 챙겨두는 것이 좋습니다.</p><h3>계약만료·기간제교사로 퇴사한 경우</h3><p>계약만료실업급여신청방법도 마찬가지로, 근로계약 기간이 끝나 재계약이 되지 않은 경우 비자발적 이직으로 처리되어 대상이 됩니다. 기간제교사실업급여신청방법 역시 계약 만료로 퇴직하는 경우라면 같은 기준이 적용됩니다. 다만 본인이 재계약을 원하지 않아 그만둔 경우라면 자발적 이직으로 처리될 수 있으니, 사업주가 발급하는 이직확인서에 이직 사유가 정확히 '계약만료'로 기재되어 있는지 확인해야 합니다.</p><h3>정년퇴직·퇴사 후 신청하는 경우</h3><p>정년퇴직실업급여(정년퇴직실업급여신청방법)를 궁금해하는 분도 많은데, 정년퇴직 역시 근로자의 의사와 무관한 이직으로 보아 실업급여 대상에 포함됩니다. 퇴사후실업급여를 신청할 수 있는지 헷갈린다면, 결국 퇴사 사유가 비자발적인지가 핵심 판단 기준이라는 점을 기억하면 됩니다.</p><h3>일용직·건설일용직인 경우</h3><p>일용직실업급여신청방법과 건설일용직실업급여신청방법은 일반 상용직과 요건이 조금 다릅니다. 일용근로자는 수급자격 인정신청일 이전 1개월간 근로일수가 10일 미만이어야 하는 등 별도 요건이 추가로 적용되므로, 고용24에서 본인의 근로 형태에 맞는 안내를 반드시 확인해야 합니다.</p><h3>예술인인 경우</h3><p>예술인구직급여는 일반 구직급여와 별도로 운영되는 예술인 고용보험 제도로, 예술인 활동으로 얻은 소득과 계약 형태를 기준으로 수급자격을 판단합니다. 일반 근로자 기준의 피보험단위기간 계산법과는 차이가 있으므로 예술인 고용보험 관련 안내를 별도로 확인하는 것이 정확합니다.</p><p><strong>대상 조건을 충족한다면 지금 바로 실업급여 계산기로 예상 수급액도 확인해보세요.</strong></p><!--CTA:1--><p>대상 여부까지 확인했다면, 이제 실제 신청 절차를 살펴볼 차례입니다.</p><p style=\"margin:32px 0;text-align:center;\"><a href=\"/posts/unemployment-benefit-application\" style=\"display:inline-block;width:100%;max-width:420px;padding:14px 20px;border-radius:8px;background-color:#03C75A;color:#ffffff;font-weight:700;font-size:1.05rem;line-height:1.4;text-decoration:none;text-align:center;\">실업급여 신청방법(고용24) 자세히 보기</a></p><p>얼마를 받을 수 있는지 정확한 계산 기준이 궁금하다면 아래 글에서 자세히 확인할 수 있습니다.</p><p style=\"margin:32px 0;text-align:center;\"><a href=\"/posts/unemployment-benefit-calculator-guide\" style=\"display:inline-block;width:100%;max-width:420px;padding:14px 20px;border-radius:8px;background-color:#03C75A;color:#ffffff;font-weight:700;font-size:1.05rem;line-height:1.4;text-decoration:none;text-align:center;\">구직급여 계산 총정리 보러가기</a></p>"
  },
  {
    "slug": "unemployment-benefit-calculator-guide",
    "title": "구직급여 계산 방법 총정리 — 2026년 상한액·하한액, 모의계산",
    "excerpt": "구직급여(실업급여) 계산 공식, 2026년 1일 상한액·하한액, 계산기로 예상 수급액을 확인하는 방법과 조기재취업수당까지 정리했습니다.",
    "date": "2026-07-22T09:10:00",
    "category": "생활정보",
    "cta": [
      {
        "label": "실업급여 계산기로 확인하기",
        "href": "https://zucca100.com/%ec%8b%a4%ec%97%85%ea%b8%89%ec%97%ac-%ea%b3%84%ec%82%b0%ea%b8%b0-%ec%88%98%ea%b8%89-%eb%8c%80%ec%83%81-%ec%a1%b0%ea%b1%b4-%ec%95%88%eb%82%b4/"
      },
      {
        "label": "지금 바로 실업급여 신청하기",
        "href": "https://m.work24.go.kr/cm/c/f/1100/selecSystInfo.do?systCnntId=CI00001715&systId=SI00000411"
      }
    ],
    "contentHtml": "<h2>구직급여 계산 — 금액, 상한액·하한액, 계산기</h2><p>구직급여계산(구직급여계산기)의 기본 공식은 '퇴직 전 3개월간 평균임금의 60% × 소정급여일수'입니다. 구직급여산정기준이 이렇다 보니, 최근 3개월 급여가 높을수록 1일 구직급여일액(구직급여일액계산)도 높아지지만, 무한정 올라가지는 않고 정해진 구직급여상한액을 넘을 수 없습니다. 2026년 기준 1일 상한액은 68,100원이며, 아무리 평균임금이 낮아도 구직급여일액하한(구직급여하한액)인 66,048원은 보장됩니다.</p><p>고용보험금액(구직급여금액, 실업급여금액)이 매년 조금씩 바뀌는 이유는 하한액이 최저임금 인상률에 연동되어 있기 때문입니다. 최근에는 최저임금이 오르면서 하한액이 기존 상한액보다 높아지는 역전 현상이 생겨, 정부가 6년 만에 상한액을 올리기도 했습니다. 이런 흐름을 두고 구직급여인상, 구직급여확대라는 표현으로 검색하는 경우도 많습니다.</p><p><strong>지금 바로 실업급여 계산기로 내 예상 수급액을 확인해보세요.</strong></p><!--CTA:0--><p>구직급여지급액을 직접 계산해보는 것보다는 실업급여모의계산(구직급여계산기)을 이용하는 편이 훨씬 정확합니다. 생년월일, 입사·퇴사일, 최근 3개월 급여 총액만 입력하면 예상 지급액과 소정급여일수를 한 번에 확인할 수 있습니다. 재취업에 성공했을 때 남은 급여일수의 일부를 받을 수 있는 조기재취업수당모의계산도 같은 방식으로 미리 확인해볼 수 있습니다.</p><p><strong>예상 수급액을 확인했다면 이제 신청할 차례입니다.</strong></p><!--CTA:1--><p>예상 금액까지 확인했다면, 실제 신청 절차와 준비물도 함께 알아두는 것이 좋습니다.</p><p style=\"margin:32px 0;text-align:center;\"><a href=\"/posts/unemployment-benefit-application\" style=\"display:inline-block;width:100%;max-width:420px;padding:14px 20px;border-radius:8px;background-color:#03C75A;color:#ffffff;font-weight:700;font-size:1.05rem;line-height:1.4;text-decoration:none;text-align:center;\">실업급여 신청방법(고용24) 자세히 보기</a></p><p>혹시 아직 대상자인지 확실하지 않다면, 상황별 조건을 먼저 확인해보는 것도 도움이 됩니다.</p><p style=\"margin:32px 0;text-align:center;\"><a href=\"/posts/unemployment-benefit-eligibility\" style=\"display:inline-block;width:100%;max-width:420px;padding:14px 20px;border-radius:8px;background-color:#03C75A;color:#ffffff;font-weight:700;font-size:1.05rem;line-height:1.4;text-decoration:none;text-align:center;\">내가 대상자인지 궁금하다면 대상·조건 총정리 보기</a></p>"
  },
  {
    "slug": "unemployment-benefit-recognition-rounds",
    "title": "실업인정 차수별 안내 — 구직급여 1차~8차 실업인정과 구직활동 인정 방법",
    "excerpt": "1차 실업인정부터 2차~8차 온라인 재인정까지, 회차별로 달라지는 절차와 인정되는 구직활동 종류를 정리했습니다.",
    "date": "2026-07-22T09:15:00",
    "category": "생활정보",
    "cta": [
      {
        "label": "고용24에서 실업인정 절차 확인하기",
        "href": "https://www.work24.go.kr/cm/main.do"
      },
      {
        "label": "실업급여 계산기로 예상 수급액 확인하기",
        "href": "https://zucca100.com/%ec%8b%a4%ec%97%85%ea%b8%89%ec%97%ac-%ea%b3%84%ec%82%b0%ea%b8%b0-%ec%88%98%ea%b8%89-%eb%8c%80%ec%83%81-%ec%a1%b0%ea%b1%b4-%ec%95%88%eb%82%b4/"
      }
    ],
    "contentHtml": "<h2>실업인정 차수별 안내 — 구직급여1차부터 8차까지</h2><p>실업급여(구직급여)는 한 번 인정받으면 끝나는 것이 아니라, 정해진 주기마다 구직활동을 보고하고 다시 인정을 받아야 합니다. 이 절차를 순서대로 구직급여1차, 구직급여2차, 구직급여3차, 구직급여4차, 구직급여5차, 구직급여6차, 구직급여7차, 구직급여8차라고 부릅니다.</p><p><strong>실업인정 신청과 관련 절차는 고용24에서 바로 확인할 수 있습니다.</strong></p><!--CTA:0--><h3>1차 실업인정 — 반드시 고용센터 방문</h3><p>1차 실업인정일에는 원칙적으로 고용센터를 직접 방문해 담당자와 면담하고 교육을 이수해야 합니다. 실업급여1차신청(실업급여1차신청방법)이 유독 까다롭게 느껴지는 이유가 여기에 있습니다.</p><h3>2차~4차 실업인정 — 온라인 재인정 가능</h3><p>2차실업급여신청방법부터는 대부분 온라인으로 재인정 신청이 가능해집니다. 실업급여2차신청방법, 실업급여3차신청방법, 실업급여4차, 실업급여4차신청방법 모두 기본적으로 이 온라인 재인정 절차를 따르며, 회차별로 요구되는 구직활동 인정 횟수는 보통 1회입니다.</p><h3>5차 이후 실업인정 — 구직활동 횟수 증가</h3><p>5차실업급여신청방법, 실업급여5차, 실업급여5차신청방법, 실업급여6차신청방법에서는 요구되는 구직활동 인정 횟수가 보통 2회로 늘어납니다. 남은 소정급여일수가 줄어들수록 재취업을 더 적극적으로 준비하도록 유도하는 구조입니다.</p><h2>구직활동 인정 방법</h2><p>실업급여구직활동(구직급여구직활동)으로 인정되는 활동에는 입사지원, 실업급여구직신청방법에 따른 워크넷 구직 등록, 구직급여면접 참여, 취업특강·박람회 참석, 직업훈련 수강, 직업상담, 자격시험 응시, 자영업 준비 등이 있습니다. 실업급여구직활동인정방법의 핵심은 이런 활동을 했다는 증빙 자료(지원 내역, 참석 확인서 등)를 실업인정일에 맞춰 제출하는 것입니다. 실업인정을 받은 회차 수만큼 급여가 지급되므로, 실업급여날짜확인(다음 실업인정일 확인)은 고용24 홈페이지에서 미리미리 해두는 것이 좋습니다.</p><p><strong>내 예상 수급액이 궁금하다면 계산기로 바로 확인해보세요.</strong></p><!--CTA:1--><p>아직 신청 전이라면, 실업인정에 앞서 기본 신청 절차부터 순서대로 확인해보는 것이 좋습니다.</p><p style=\"margin:32px 0;text-align:center;\"><a href=\"/posts/unemployment-benefit-application\" style=\"display:inline-block;width:100%;max-width:420px;padding:14px 20px;border-radius:8px;background-color:#03C75A;color:#ffffff;font-weight:700;font-size:1.05rem;line-height:1.4;text-decoration:none;text-align:center;\">실업급여 신청방법(고용24) 자세히 보기</a></p><p>실업인정을 받은 뒤에는 실제로 언제, 얼마가 들어오는지도 함께 알아두면 좋습니다.</p><p style=\"margin:32px 0;text-align:center;\"><a href=\"/posts/unemployment-benefit-payment-info\" style=\"display:inline-block;width:100%;max-width:420px;padding:14px 20px;border-radius:8px;background-color:#03C75A;color:#ffffff;font-weight:700;font-size:1.05rem;line-height:1.4;text-decoration:none;text-align:center;\">실업인정 이후 지급일이 궁금하다면 지급일 안내 보기</a></p>"
  },
  {
    "slug": "unemployment-benefit-payment-info",
    "title": "실업급여 지급일·세금·국민연금 총정리 — 대기기간·연장·아르바이트까지",
    "excerpt": "실업급여 지급 기간과 대기기간, 지급일, 비과세 여부, 국민연금 실업크레딧, 수급 중 아르바이트·직업훈련 신고 방법까지 정리했습니다.",
    "date": "2026-07-22T09:20:00",
    "category": "생활정보",
    "cta": [
      {
        "label": "지금 바로 고용24에서 신청 절차 확인하기",
        "href": "https://m.work24.go.kr/cm/c/f/1100/selecSystInfo.do?systCnntId=CI00001715&systId=SI00000411"
      },
      {
        "label": "실업급여 계산기로 예상 수급액 확인하기",
        "href": "https://zucca100.com/%ec%8b%a4%ec%97%85%ea%b8%89%ec%97%ac-%ea%b3%84%ec%82%b0%ea%b8%b0-%ec%88%98%ea%b8%89-%eb%8c%80%ec%83%81-%ec%a1%b0%ea%b1%b4-%ec%95%88%eb%82%b4/"
      }
    ],
    "contentHtml": "<h2>지급 기간·지급일 — 구직급여기간부터 대기기간까지</h2><p>구직급여기간(실업급여기간, 구직급여수급기간)은 연령과 고용보험 가입기간에 따라 120일에서 최대 270일까지 차등 지급됩니다. 가입기간이 길고 나이가 많을수록 받을 수 있는 총 지급일수도 늘어나는 구조입니다.</p><p>수급자격을 인정받아도 곧바로 돈이 들어오는 것은 아닙니다. 실업급여대기기간이라고 부르는 7일간은 원칙적으로 급여가 지급되지 않으며, 그 이후 실업인정을 받은 날부터 구직급여지급일이 정해집니다. 실업급여당일지급이라는 표현으로 검색하는 분도 많지만, 실제로는 실업인정 이후 며칠 내로 구직급여입금이 이뤄지는 구조여서 신청 당일 바로 입금된다는 뜻은 아니라는 점을 알아두어야 합니다. 소정급여일수를 다 채우지 못하고 재취업했거나 부득이한 사유가 있다면 구직급여연장 신청이 가능한 경우도 있으니 관할 고용센터에 문의하는 것이 정확합니다.</p><p><strong>지금 바로 고용24에서 신청 절차를 확인해보세요.</strong></p><!--CTA:0--><h2>세금·국민연금 — 알아두면 유리한 것들</h2><p>구직급여세금 여부를 궁금해하는 분들이 많은데, 실업급여(구직급여)는 비과세 소득으로 분류되어 별도로 세금을 떼지 않습니다.</p><p>구직급여수급기간중국민연금가입기간추가산입희망여부라는 항목이 신청서에 포함되어 있는데, 이는 실업급여를 받는 동안 국민연금 보험료 일부를 지원받아 그 기간을 국민연금 가입기간으로 추가 인정해주는 '실업크레딧' 제도 신청 여부를 묻는 것으로, 구직급여국민연금과 관련된 항목입니다. 신청해두면 국민연금 가입기간을 늘리는 데 유리한 경우가 많습니다.</p><h2>아르바이트, 직업훈련, 심리검사</h2><p>구직급여알바(실업급여 수급 중 아르바이트)는 원칙적으로 금지되지 않지만, 반드시 실업인정일마다 근로 사실을 신고해야 합니다. 신고하지 않고 근로한 사실이 나중에 드러나면 부정수급으로 간주되어 지급된 급여를 반환하고 추가 징수까지 당할 수 있으므로 주의해야 합니다.</p><p>구직급여직업훈련을 받고 싶다면 내일배움카드실업급여 연계 훈련과정을 활용할 수 있고, 이 경우 구직급여취업 활동 인정에도 도움이 됩니다. 수급자격 인정신청 과정에는 구직급여심리검사(직업선호도검사 등 워크넷 심리검사)가 포함되기도 하는데, 이는 본인에게 맞는 재취업 방향을 찾기 위한 참고 자료로 활용됩니다.</p><p>관할 고용보험센타(정식 명칭은 고용센터)를 방문할 일이 있다면 반드시 신분증을 지참해야 합니다.</p><p><strong>내 예상 수급액이 궁금하다면 계산기로 확인해보세요.</strong></p><!--CTA:1--><p>아직 신청 전이라면 기본적인 신청 절차와 준비물부터 순서대로 확인해보는 것이 좋습니다.</p><p style=\"margin:32px 0;text-align:center;\"><a href=\"/posts/unemployment-benefit-application\" style=\"display:inline-block;width:100%;max-width:420px;padding:14px 20px;border-radius:8px;background-color:#03C75A;color:#ffffff;font-weight:700;font-size:1.05rem;line-height:1.4;text-decoration:none;text-align:center;\">실업급여 신청방법(고용24) 자세히 보기</a></p><p>지급일과 함께, 신청 이후 반복되는 실업인정 절차도 미리 알아두면 당황하지 않습니다.</p><p style=\"margin:32px 0;text-align:center;\"><a href=\"/posts/unemployment-benefit-recognition-rounds\" style=\"display:inline-block;width:100%;max-width:420px;padding:14px 20px;border-radius:8px;background-color:#03C75A;color:#ffffff;font-weight:700;font-size:1.05rem;line-height:1.4;text-decoration:none;text-align:center;\">실업인정 차수별 안내(1차~8차) 보기</a></p>"
  },
  {
    "slug": "hamyang-daebongsan-monorail-guide",
    "title": "함양 대봉산 모노레일 정보 총정리 — 예약·요금·시간표·주차·반려동반·맛집",
    "excerpt": "함양 대봉산 모노레일 예약 방법부터 요금, 시간표, 주차, 반려동물 동반, 근처 맛집까지 한 번에 정리했습니다.",
    "date": "2026-07-23T09:00:00",
    "category": "여행/나들이",
    "cta": [
      { "label": "지금 바로 대봉산 모노레일 예약 페이지 확인하기", "href": "https://www.hygn.go.kr/02147/02171/05263.web" },
      { "label": "남은 좌석 지금 확인해보기", "href": "https://www.hygn.go.kr/02147/02171/05263.web" },
      { "label": "대봉산 모노레일 예약 바로가기", "href": "https://www.hygn.go.kr/02147/02171/05263.web" }
    ],
    "contentHtml": "<h2>함양 대봉산 모노레일이란?</h2><p>함양 대봉산 모노레일은 경상남도 함양군 병곡면 대봉산휴양밸리 안에 있는 산악 관광 모노레일입니다. 하부승강장에서 대봉산모노레일상부승강장(해발 1,200m대 정상부 인근)까지 약 3.93km 구간을 오르내리며, 국내에서 손꼽히는 장거리 산악 모노레일로 알려져 있습니다. 검색할 때는 대봉산모노레일, 대봉모노레일, 함양대봉모노레일, 함양대봉산, 함양대봉산모노레일, 함양군대봉산모노레일, 대봉산휴양밸리모노레일, 함양대봉산휴양밸리, 함양모노레일, 함양모노레일예약, 경남함양모노레일처럼 표현이 조금씩 다르지만 모두 같은 시설을 가리킵니다. 간혹 함안모노레일이라고 검색하는 경우도 있는데, 함안군은 인접한 다른 지자체이고 이 모노레일이 있는 곳은 함양군이니 헷갈리지 않도록 주의하세요.</p><p>왕복 전체 코스를 이용하면 약 1시간(65분) 안팎이 걸리고, 편도로는 약 30분 정도 소요됩니다. 8인승 캐빈이 순환 운행하며 상행과 하행 노선이 달라 오갈 때 서로 다른 경치를 볼 수 있습니다.</p><!--CTA:0--><h2>함양 대봉산 모노레일 예약 방법</h2><p>대봉산모노레일예약(함양대봉산모노레일예약)은 대봉산모노레일홈페이지(함양군 대봉산휴양밸리 공식 홈페이지)에서 시작합니다. 홈페이지의 예약 바로가기 버튼을 누르면 야놀자 예매 시스템으로 연결되고, 탑승 날짜와 시간대, 인원을 선택한 뒤 본인 인증과 결제를 마치면 예약이 끝납니다. 대봉산모노레일예약방법, 대봉산모노레일예약사이트, 대봉산모노레일예약홈페이지, 대봉산모노레일예약하는법, 함양대봉산모노레일예약방법, 함양대봉산모노레일예약사이트, 함양대봉산휴양밸리모노레일예약처럼 표현은 달라도 모두 이 절차를 가리킵니다.</p><p>대봉산모노레일예매(대봉산모노레일예약)는 탑승일 전날 밤 23시 59분까지 온라인으로 가능하며, 당일 예약은 온라인으로 열리지 않고 현장에서만 처리됩니다. 함양대봉산모노레일예약하기 전에는 회원가입 없이도 이름과 휴대폰 번호만으로 진행할 수 있고, 예매가 완료되면 모바일 티켓이 발송됩니다.</p><h2>예약 없이 현장에서 바로 탈 수 있을까?</h2><p>대봉산모노레일예약없이(함양대봉산모노레일예약없이) 방문해도 그날 잔여 좌석이 남아 있으면 현장에서 구매해 탑승할 수 있습니다. 이를 대봉산모노레일현장, 대봉산모노레일현장구매, 대봉산모노레일현장발권, 대봉산모노레일현장예매라고 부르기도 합니다. 다만 주말이나 성수기 오전 시간대는 예약이 열리자마자 며칠 만에 마감되는 경우가 잦아, 확실하게 타고 싶다면 최소 일주일 전에는 온라인 예약을 마치는 편이 안전합니다.</p><h2>대봉산 모노레일 요금(가격)</h2><p>대봉산모노레일가격(대봉산모노레일요금, 함양대봉산모노레일예약가격)은 왕복 기준으로 성인(19~64세) 15,000원, 청소년·경로우대자·군인·장애인·유공자·20인 이상 단체는 12,000원, 36개월~12세 어린이나 각종 할인권 소지자는 10,000원이며, 36개월 미만 유아는 무료로 안내되고 있습니다. 대봉산모노레일요금은 시즌이나 정책 변경에 따라 조정될 수 있으므로, 정확한 금액은 예약 직전 공식 홈페이지나 예약 화면에서 다시 한 번 확인하는 것이 안전합니다. 단체 할인이나 대봉산모노레일할인 혜택 대상에 해당하는지도 예약 전에 함께 확인해두면 좋습니다.</p><h2>운영시간·시간표·소요시간</h2><p>대봉산모노레일시간표(대봉산모노레일시간)는 오전 9시 30분부터 오후 4시 30분까지이며, 마지막 탑승은 보통 오후 3시 30분 전후로 마감됩니다. 대봉산모노레일소요시간은 편도 약 30분, 하부승강장에서 상부승강장까지 왕복 전체 코스를 이용하면 1시간(65분) 안팎이 걸립니다. 대봉산모노레일운행간격 자체는 예약한 시간대에 맞춰 순차 탑승하는 방식이라 지하철처럼 몇 분 간격으로 딱 떨어지지는 않지만, 승강장을 오가는 무료 셔틀버스는 15~20분 간격으로 운행하고 마지막 셔틀은 오후 4시(양방향 기준 오후 5시 55분까지)까지 다닙니다. 캐빈 내부에는 대봉산모노레일에어컨 등 냉방 시설이 갖춰져 있어 한여름에도 비교적 쾌적하게 이용할 수 있습니다.</p><p><strong>지금 바로 원하는 날짜와 시간대가 남아있는지 확인해보세요.</strong></p><!--CTA:1--><h2>대봉산모노레일 지금 영업 중인지 확인하는 법</h2><p>대봉산모노레일휴장일은 매주 화요일과 매달 마지막 주 수요일이며, 정기 안전 점검일에도 운행하지 않습니다. 대봉산모노레일지금영업중, 대봉산모노레일예약지금영업중처럼 검색해서 오늘 당장 갈 수 있는지 확인하고 싶다면, 위 정기 휴장일에 해당하는지부터 먼저 살펴보세요. 강풍 등 기상 상황에 따라 비정기적으로 운행이 중단될 수도 있으므로, 대봉산모노레일정상운행 여부는 방문 당일 아침 공식 홈페이지 공지나 전화 문의로 다시 한 번 확인하는 것이 가장 정확합니다.</p><h2>가는 길·주차·문의 전화번호</h2><p>대봉산모노레일주차(대봉산모노레일주차장)는 대봉산휴양밸리 내 주차장을 이용하면 되고, 주말과 성수기에는 혼잡할 수 있어 예약 시간 40~45분 전에는 도착하는 것이 좋습니다. 시설 이용 문의는 055-963-2025(대봉스카이랜드), 온라인 예약 관련 문의는 1644-1346(야놀자 고객센터)이며, 두 번호 모두 대봉산모노레일전화번호로 통합니다.</p><h2>예약 확인·취소·환불</h2><p>대봉산모노레일예약확인(함양대봉산모노레일예약확인)은 예약 시 안내되는 모바일 티켓이나 야놀자 예약 내역에서 할 수 있습니다. 대봉산모노레일예약취소(대봉산모노레일취소, 함양대봉산모노레일예약취소)는 야놀자 예약 내역 화면에서 직접 진행하며, 취소 시점에 따라 수수료나 환불 가능 여부가 달라질 수 있으니 취소 규정은 예약 화면에서 미리 확인해두는 것이 좋습니다.</p><h2>반려동물(강아지)과 함께 탈 수 있을까?</h2><p>대봉산모노레일강아지, 대봉산모노레일반려견, 대봉산모노레일애견동반 여부는 안내마다 조금씩 엇갈려서 헷갈리기 쉬운 주제입니다. 이동장(켄넬) 사용 여부, 크기 제한, 시설 방침에 따라 달라질 수 있는 부분이라 확인 방법과 준비물을 별도 글에서 자세히 정리했습니다.</p><p style=\"margin:32px 0;text-align:center;\"><a href=\"/posts/daebongsan-monorail-pet-guide\" style=\"display:inline-block;width:100%;max-width:420px;padding:14px 20px;border-radius:8px;background-color:#03C75A;color:#ffffff;font-weight:700;font-size:1.05rem;line-height:1.4;text-decoration:none;text-align:center;\">반려동물 동반 확인 방법 보러가기</a></p><h2>대봉산모노레일 근처 맛집</h2><p>대봉산모노레일근처맛집(대봉산모노레일맛집, 대봉산모노레일주변맛집, 대봉산모노레일식당)을 찾는 분들을 위해, 휴양밸리 안팎의 식사 장소를 메뉴와 위치 위주로 별도 글에 정리했습니다.</p><p style=\"margin:32px 0;text-align:center;\"><a href=\"/posts/daebongsan-monorail-restaurant-guide\" style=\"display:inline-block;width:100%;max-width:420px;padding:14px 20px;border-radius:8px;background-color:#03C75A;color:#ffffff;font-weight:700;font-size:1.05rem;line-height:1.4;text-decoration:none;text-align:center;\">근처 맛집 리스트 보러가기</a></p><h2>단풍철 방문 팁과 후기 포인트</h2><p>대봉산모노레일단풍은 가을철 인기 있는 방문 이유 중 하나로, 상부승강장 부근에서 내려다보는 산세와 단풍이 어우러진 풍경이 대봉산모노레일후기에서 자주 언급됩니다. 다만 단풍 시기는 해마다 기온에 따라 달라질 수 있으니, 방문 전 지역 산림 관련 기관이나 함양군 공지를 통해 최근 단풍 상황을 확인하고 일정을 잡는 것이 좋습니다.</p><h2>자주 묻는 질문</h2><p><strong>Q1. 대봉산모노레일예약없이 당일 현장에서 바로 탈 수 있나요?</strong> 잔여 좌석이 있으면 가능하지만, 주말·성수기에는 매진이 잦아 사전 예약을 권장합니다.</p><p><strong>Q2. 대봉산모노레일요금은 매년 똑같이 유지되나요?</strong> 정책과 물가에 따라 조정될 수 있어, 방문 전 예약 화면에서 최신 요금을 다시 확인하는 것이 안전합니다.</p><p><strong>Q3. 대봉산모노레일주차장 이용료가 따로 있나요?</strong> 주차 요금 정책은 운영 주체 공지에 따라 달라질 수 있으니 방문 전 공식 채널로 확인하는 것이 정확합니다.</p><p><strong>지금 바로 대봉산 모노레일 예약 페이지로 이동해 원하는 시간대를 확인해보세요.</strong></p><!--CTA:2-->"
  },
  {
    "slug": "daebongsan-monorail-pet-guide",
    "title": "대봉산모노레일 반려동물(강아지) 동반 가능할까? 확인 방법",
    "excerpt": "대봉산모노레일 반려견·강아지 동반 탑승이 가능한지, 확인 방법과 준비물을 정리했습니다.",
    "date": "2026-07-23T09:01:00",
    "category": "여행/나들이",
    "contentHtml": "<h2>대봉산모노레일 반려동물 동반, 왜 정보가 엇갈릴까?</h2><p>대봉산모노레일강아지, 대봉산모노레일반려견, 대봉산모노레일애견동반 여부를 검색하면 안내가 조금씩 다르게 나옵니다. 이동장(켄넬)에 넣으면 동반 탑승이 가능하다는 안내가 있는 반면, 안전이나 다른 이용객과의 공간 공유 문제로 별도 제한이 있을 수 있다는 안내도 함께 확인됩니다. 이런 시설 이용 규정은 운영 주체 방침이나 시기에 따라 바뀔 수 있어 온라인 정보만으로 단정하기 어렵습니다.</p><h2>방문 전 확인해야 할 것</h2><p>반려동물과 함께 대봉산모노레일 탑승을 계획한다면 아래 내용을 방문 전에 직접 확인해두는 것이 가장 확실합니다.</p><p>1. 이동장(켄넬) 필수 여부와 크기 제한<br>2. 캐빈 1대당 동반 가능한 반려동물 마리 수<br>3. 대형견 등 크기가 큰 반려동물의 탑승 가능 여부<br>4. 예약 단계에서 반려동물 동반 여부를 별도로 표시해야 하는지</p><p>확인은 시설 이용 문의 전화인 055-963-2025(대봉스카이랜드)로 하는 것이 가장 정확합니다. 예약 관련 문의(1644-1346, 야놀자 고객센터)는 결제·예약 절차 문의 창구이므로, 반려동물 동반 가능 여부처럼 시설 자체 운영 규정에 관한 질문은 대봉스카이랜드 쪽에 직접 확인하는 편이 낫습니다.</p><h2>반려동물과 함께라면 이렇게 준비하세요</h2><p>동반이 가능하다는 답변을 받았다면 이동장, 배변 패드, 물, 하네스 등을 미리 챙기고, 다른 탑승객과 같은 캐빈을 이용하는 경우가 많다는 점을 감안해 짖음이나 돌발 행동에 대비하는 것이 좋습니다. 만약 동반이 어렵다고 안내받았다면, 예약 전 반려동물을 맡길 수 있는 장소를 미리 알아보고 일정을 조정하는 것이 안전합니다.</p><h2>자주 묻는 질문</h2><p><strong>Q1. 대봉산모노레일애견동반이 확실히 가능한가요?</strong> 안내가 엇갈리는 부분이라 이 글에서 단정하지 않습니다. 방문 전 055-963-2025로 직접 확인하는 것이 가장 정확합니다.</p><p><strong>Q2. 이동장 없이도 반려견을 안고 탑승할 수 있나요?</strong> 다른 탑승객과의 안전을 고려해 이동장을 요구하는 경우가 일반적이므로, 이동장을 준비해가는 것이 안전합니다.</p><p>모노레일 예약 방법, 요금, 시간표 등 전체 이용 정보는 아래 글에서 한 번에 확인할 수 있습니다.</p><p style=\"margin:32px 0;text-align:center;\"><a href=\"/posts/hamyang-daebongsan-monorail-guide\" style=\"display:inline-block;width:100%;max-width:420px;padding:14px 20px;border-radius:8px;background-color:#03C75A;color:#ffffff;font-weight:700;font-size:1.05rem;line-height:1.4;text-decoration:none;text-align:center;\">함양 대봉산 모노레일 예약·요금·시간표 총정리 보러가기</a></p>"
  },
  {
    "slug": "daebongsan-monorail-restaurant-guide",
    "title": "대봉산모노레일 근처 맛집 — 휴양밸리 안팎 식사 장소 정리",
    "excerpt": "대봉산모노레일 근처맛집·주변맛집·식당 정보를 위치와 메뉴 위주로 정리했습니다.",
    "date": "2026-07-23T09:02:00",
    "category": "여행/나들이",
    "contentHtml": "<h2>대봉산모노레일 근처맛집, 어디서 먹을까?</h2><p>대봉산모노레일근처맛집(대봉산모노레일맛집, 대봉산모노레일주변맛집)을 찾는다면 크게 두 가지 선택지가 있습니다. 하나는 대봉산휴양밸리 단지 안에서 바로 해결하는 방법이고, 다른 하나는 차로 잠깐 이동해 인근 식당을 찾아가는 방법입니다.</p><h2>휴양밸리 안에서 바로 먹을 수 있는 곳</h2><p>대봉산모노레일식당을 단지 밖으로 나가지 않고 해결하고 싶다면 휴양밸리 내 대봉산식당과 대봉먹거리관을 이용할 수 있습니다. 모노레일과 짚라인을 이용하는 김에 이동 동선 안에서 식사까지 마칠 수 있어 시간을 아낄 수 있다는 점이 장점입니다.</p><h2>차로 잠깐 이동하는 인근 맛집</h2><p>조금 더 여유가 있다면 인근에서 소개되는 식당으로 까치식당(닭갈비), 박서방해물칼국수, 대성식당(한우국밥) 등이 있습니다. 다만 맛집 정보는 운영 시간이나 휴무일이 바뀔 수 있어, 방문 전 전화나 지도 앱으로 영업 여부를 한 번 더 확인하는 것이 안전합니다.</p><h2>모노레일 이용 시간과 맞춰 식사 시간 정하기</h2><p>대봉산모노레일 예약 시간대에 맞춰 식사 순서를 정하면 동선이 편해집니다. 오전 일찍 모노레일을 탑승할 계획이라면 탑승 전 간단히 먹고 다녀온 뒤 여유 있게 점심을 먹는 방식도 좋고, 반대로 식사를 먼저 마치고 오후 시간대로 예약하는 방법도 있습니다. 마지막 탑승 시각을 놓치지 않도록, 식사 장소에서 승강장까지 이동 시간을 넉넉히 잡아두는 것이 좋습니다.</p><h2>자주 묻는 질문</h2><p><strong>Q1. 휴양밸리 안 식당과 인근 맛집 중 어디가 나을까요?</strong> 시간이 촉박하면 휴양밸리 내 식당이, 여유가 있다면 인근 맛집이 선택지가 될 수 있습니다. 취향과 일정에 따라 고르면 됩니다.</p><p><strong>Q2. 주말에는 예약 없이도 식당을 이용할 수 있나요?</strong> 식당별로 상황이 다를 수 있어, 인원이 많다면 미리 전화로 확인하는 것이 안전합니다.</p><p>모노레일 예약 방법과 요금, 시간표 등 전체 이용 정보가 궁금하다면 아래 글을 확인하세요.</p><p style=\"margin:32px 0;text-align:center;\"><a href=\"/posts/hamyang-daebongsan-monorail-guide\" style=\"display:inline-block;width:100%;max-width:420px;padding:14px 20px;border-radius:8px;background-color:#03C75A;color:#ffffff;font-weight:700;font-size:1.05rem;line-height:1.4;text-decoration:none;text-align:center;\">함양 대봉산 모노레일 예약·요금·시간표 총정리 보러가기</a></p>"
  }
]
